iana_bcp47/__init__.py
iana_bcp47/bcp47.py
iana_bcp47/fetcher.py
iana_bcp47/validator.py
test/__init__.py
test/highfestiva_bcp47.py
test/readme_test.py
test/simple_test.py
iana_bcp47-0.1.2.dist-info/LICENSE
iana_bcp47-0.1.2.dist-info/METADATA
iana_bcp47-0.1.2.dist-info/WHEEL
iana_bcp47-0.1.2.dist-info/top_level.txt
iana_bcp47-0.1.2.dist-info/RECORD
