Metadata-Version: 2.1
Name: iana-bcp47
Version: 0.1.2
Summary: A Python package to validate BCP47 language tags
Home-page: https://github.com/Masterain98/iana-bcp47
Author: Masterain98
Author-email: i@irain.in
Classifier: Programming Language :: Python :: 3
Classifier: License :: OSI Approved :: MIT License
Classifier: Operating System :: OS Independent
Requires-Python: >=3.9
License-File: LICENSE
